request_pm_rqiza/__init__.py
request_pm_rqiza/my_code.py
request_pm_rqiza-0.1.1.dist-info/METADATA
request_pm_rqiza-0.1.1.dist-info/WHEEL
request_pm_rqiza-0.1.1.dist-info/top_level.txt
request_pm_rqiza-0.1.1.dist-info/RECORD
